odoo/addons/web_sort_menu/README.rst
odoo/addons/web_sort_menu/__init__.py
odoo/addons/web_sort_menu/__manifest__.py
odoo/addons/web_sort_menu/i18n/web_sort_menu.pot
odoo/addons/web_sort_menu/readme/CONTRIBUTORS.md
odoo/addons/web_sort_menu/readme/DESCRIPTION.md
odoo/addons/web_sort_menu/readme/USAGE.md
odoo/addons/web_sort_menu/static/description/icon.png
odoo/addons/web_sort_menu/static/description/index.html
odoo/addons/web_sort_menu/static/src/js/sort_app_menu.esm.js
odoo/addons/web_sort_menu/static/src/xml/sort_app_menu.xml
odoo_addon_web_sort_menu-18.0.1.0.0.2.dist-info/METADATA
odoo_addon_web_sort_menu-18.0.1.0.0.2.dist-info/WHEEL
odoo_addon_web_sort_menu-18.0.1.0.0.2.dist-info/top_level.txt
odoo_addon_web_sort_menu-18.0.1.0.0.2.dist-info/RECORD
